compress_image/__init__.py
compress_image/compress_image.py
compress_image/main.py
compress_image-1.0.2.dist-info/LICENSE
compress_image-1.0.2.dist-info/METADATA
compress_image-1.0.2.dist-info/WHEEL
compress_image-1.0.2.dist-info/entry_points.txt
compress_image-1.0.2.dist-info/top_level.txt
compress_image-1.0.2.dist-info/RECORD
