Metadata-Version: 2.1
Name: compress-image
Version: 1.0.2
Summary: Compress Image Utils
Home-page: https://github.com/tienthienhd/compress_image
Author: Thien NT
Author-email: tienthienhd@gmail.com
License: LICENSE
Keywords: Image Utils,Image Compress
Platform: UNKNOWN
Classifier: Programming Language :: Python :: 3.6
Classifier: Programming Language :: Python :: 3.7
Requires-Dist: Pillow
